gimfu/__init__.py
gimfu/config.py
gimfu/easy_date.py
gimfu/extract_inj_geners.py
gimfu/extract_inj_grps.py
gimfu/extract_prd_geners.py
gimfu/extract_prd_grps.py
gimfu/figure_report.py
gimfu/gener_groups.py
gimfu/geo_common.py
gimfu/gpl.py
gimfu/make_scenarios.py
gimfu/multiple_listings_plotting.py
gimfu/project_cli.py
gimfu/save2incon.py
gimfu/scenario_extraction.py
gimfu/scenario_spec_report.py
gimfu/scenario_utils.py
gimfu/t2listingh5.py
gimfu/wells.py
gimfu-0.0.7.dist-info/METADATA
gimfu-0.0.7.dist-info/WHEEL
gimfu-0.0.7.dist-info/entry_points.txt
gimfu-0.0.7.dist-info/licenses/LICENSE.txt
gimfu-0.0.7.dist-info/RECORD
