Metadata-Version: 2.4
Name: gimfu
Version: 0.0.7
Summary: A toolkit and python library for generating future scenarios in AUTOUGH2.
Project-URL: Documentation, https://github.com/cyeh015/gimfu/blob/main/README.md
Project-URL: Issues, https://github.com/cyeh015/gimfu/issues
Project-URL: Source, https://github.com/cyeh015/gimfu
Author-email: Angus Yeh <a.yeh@auckland.ac.nz>
License-Expression: MIT
License-File: LICENSE.txt
Classifier: Development Status :: 4 - Beta
Classifier: Programming Language :: Python
Classifier: Programming Language :: Python :: 3.8
Classifier: Programming Language :: Python :: 3.9
Classifier: Programming Language :: Python :: 3.10
Classifier: Programming Language :: Python :: 3.11
Classifier: Programming Language :: Python :: Implementation :: CPython
Classifier: Programming Language :: Python :: Implementation :: PyPy
Requires-Python: >=3.8
Requires-Dist: h5py
Requires-Dist: matplotlib
Requires-Dist: numpy
Requires-Dist: pint
Requires-Dist: pytough
Requires-Dist: scipy
Requires-Dist: tabulate
Requires-Dist: xlsxwriter
Requires-Dist: xlwt
